LICENSE
README.md
setup.py
pdf_Creator_mr.egg-info/PKG-INFO
pdf_Creator_mr.egg-info/SOURCES.txt
pdf_Creator_mr.egg-info/dependency_links.txt
pdf_Creator_mr.egg-info/requires.txt
pdf_Creator_mr.egg-info/top_level.txt
pdf_generator/__init__.py
pdf_generator/pdf_creator.py
tests/test_pdf_creator.py