Metadata-Version: 2.1
Name: pdf-Creator-mr
Version: 0.0.2
Home-page: https://github.com/mateusdosreisf/pdf_generator
Author: Mateus Reis
Author-email: mateussgp12@gmail.com
License-File: LICENSE
Requires-Dist: reportlab
